cpol_pyscf/PySCFmerger.py
cpol_pyscf/__init__.py
cpol_pyscf/momtensor.py
cpol_pyscf/poltensor.py
cpol_pyscf/qdist.py
cpol_pyscf-0.1.16.dist-info/licenses/LICENSE
cpol_pyscf-0.1.16.dist-info/METADATA
cpol_pyscf-0.1.16.dist-info/WHEEL
cpol_pyscf-0.1.16.dist-info/top_level.txt
cpol_pyscf-0.1.16.dist-info/RECORD
