Metadata-Version: 2.4
Name: cpol_pyscf
Version: 0.1.16
Summary: A package for calculating molecular moments and polarizabilities using PySCF
Home-page: https://github.com/pypa/sampleproject
Author: 
Author-email: mailanoopanair@gmail.com
Classifier: Programming Language :: Python :: 3
Classifier: License :: OSI Approved :: MIT License
Classifier: Operating System :: OS Independent
Requires-Python: >=3.6
License-File: LICENSE
Requires-Dist: numpy
Requires-Dist: scipy
Requires-Dist: pyscf
Requires-Dist: matplotlib
Requires-Dist: ase
Dynamic: author-email
Dynamic: classifier
Dynamic: description
Dynamic: description-content-type
Dynamic: home-page
Dynamic: license-file
Dynamic: requires-dist
Dynamic: requires-python
Dynamic: summary
